asvc/__init__.py
asvc/__main__.py
asvc/_version.py
asvc/backends/__init__.py
asvc/backends/kafka/__init__.py
asvc/backends/kafka/broker.py
asvc/backends/nats/__init__.py
asvc/backends/nats/broker.py
asvc/backends/nats/middlewares.py
asvc/backends/pubsub.py
asvc/backends/rabbitmq/__init__.py
asvc/backends/rabbitmq/broker.py
asvc/backends/rabbitmq/middlewares.py
asvc/backends/redis/__init__.py
asvc/backends/redis/broker.py
asvc/backends/redis/middlewares.py
asvc/backends/stub.py
asvc/broker.py
asvc/cli.py
asvc/consumer.py
asvc/encoders/__init__.py
asvc/encoders/json.py
asvc/encoders/msgpack.py
asvc/encoders/orjson.py
asvc/encoders/pickle.py
asvc/exceptions.py
asvc/logger.py
asvc/middleware.py
asvc/middlewares/__init__.py
asvc/middlewares/debug.py
asvc/middlewares/error.py
asvc/middlewares/healthcheck.py
asvc/middlewares/opentelemetry.py
asvc/middlewares/prometheus.py
asvc/middlewares/retries.py
asvc/models.py
asvc/py.typed
asvc/service.py
asvc/types.py
asvc/utils/__init__.py
asvc/utils/datetime.py
asvc/utils/enum.py
asvc/utils/functools.py
asvc/web.py
asvc-0.1.0.dist-info/entry_points.txt
asvc-0.1.0.dist-info/LICENSE
asvc-0.1.0.dist-info/WHEEL
asvc-0.1.0.dist-info/METADATA
asvc-0.1.0.dist-info/RECORD
