Metadata-Version: 2.1
Name: asvc
Version: 0.1.0
Summary: Event driven microservice framework for python
Author: Radzim Kowalow
Author-email: radzim_ko@wp.pl
Requires-Python: >=3.7,<4.0
Classifier: Programming Language :: Python :: 3
Classifier: Programming Language :: Python :: 3.7
Classifier: Programming Language :: Python :: 3.8
Classifier: Programming Language :: Python :: 3.9
Classifier: Programming Language :: Python :: 3.10
Classifier: Programming Language :: Python :: 3.11
Provides-Extra: all
Provides-Extra: cli
Provides-Extra: kafka
Provides-Extra: msgpack
Provides-Extra: nats
Provides-Extra: opentelemetry
Provides-Extra: orjson
Provides-Extra: prometheus
Provides-Extra: pubsub
Provides-Extra: rabbitmq
Provides-Extra: redis
Provides-Extra: zmq
Requires-Dist: aio-pika (>=8.0.3,<9.0.0); extra == "all" or extra == "rabbitmq"
Requires-Dist: aiohttp (>=3.8.1,<4.0.0)
Requires-Dist: aiokafka (>=0.7.2,<0.8.0); extra == "all" or extra == "kafka"
Requires-Dist: aioredis (>=2.0.1,<3.0.0); extra == "all" or extra == "redis"
Requires-Dist: aiorun (>=2022.4.1,<2023.0.0); extra == "all" or extra == "cli"
Requires-Dist: async-timeout (>=4.0.2,<5.0.0)
Requires-Dist: click (>=8.1.3,<9.0.0); extra == "all" or extra == "cli"
Requires-Dist: gcloud-aio-pubsub (>=5.0.0,<6.0.0); extra == "all" or extra == "pubsub"
Requires-Dist: nats-py (>=2.1.3,<3.0.0); extra == "all" or extra == "nats"
Requires-Dist: opentelemetry-api (>=1.13.0,<2.0.0); extra == "all" or extra == "opentelemetry"
Requires-Dist: opentelemetry-sdk (>=1.13.0,<2.0.0); extra == "all" or extra == "opentelemetry"
Requires-Dist: orjson (>=3.7.1,<4.0.0); extra == "all" or extra == "orjson"
Requires-Dist: ormsgpack (>=1.2.3,<2.0.0); extra == "all" or extra == "msgpack"
Requires-Dist: prometheus-client (>=0.14.1,<0.15.0); extra == "all" or extra == "prometheus"
Requires-Dist: pydantic (>=1.9.1,<2.0.0)
Requires-Dist: uvloop (>=0.16.0,<0.17.0)
